pushup_counter.py
pushup_counter-0.0.1.dist-info/METADATA
pushup_counter-0.0.1.dist-info/WHEEL
pushup_counter-0.0.1.dist-info/top_level.txt
pushup_counter-0.0.1.dist-info/RECORD
